condor_tensorflow/__init__.py
condor_tensorflow/activations.py
condor_tensorflow/labelencoder.py
condor_tensorflow/loss.py
condor_tensorflow/metrics.py
condor_tensorflow/version.py
condor_tensorflow-1.0.1.dist-info/LICENSE
condor_tensorflow-1.0.1.dist-info/METADATA
condor_tensorflow-1.0.1.dist-info/WHEEL
condor_tensorflow-1.0.1.dist-info/top_level.txt
condor_tensorflow-1.0.1.dist-info/RECORD
