Metadata-Version: 2.1
Name: condor-tensorflow
Version: 1.0.1
Summary: A tensorflow implementation of Conditionals for Ordinal Regression
Home-page: https://github.com/GarrettJenkinson/condor_tensorflow
Author: Garrett Jenkinson
Author-email: Jenkinson.William@mayo.edu
License: UNKNOWN
Project-URL: Bug Tracker, https://github.com/GarrettJenkinson/condor_tensorflow/issues
Platform: UNKNOWN
Classifier: Programming Language :: Python :: 3
Classifier: License :: OSI Approved :: MIT License
Classifier: Operating System :: OS Independent
Requires-Python: >=3.6
License-File: LICENSE
